torchcqrn/__init__.py
torchcqrn/cqrn.py
PyTorch_CQRN-0.1.2.dist-info/LICENSE
PyTorch_CQRN-0.1.2.dist-info/METADATA
PyTorch_CQRN-0.1.2.dist-info/WHEEL
PyTorch_CQRN-0.1.2.dist-info/top_level.txt
PyTorch_CQRN-0.1.2.dist-info/RECORD
