Metadata-Version: 2.1
Name: PyTorch-CQRN
Version: 0.1.2
Summary: Convolutional Quasi-Recurrent Network (CQRN)
Home-page: https://github.com/syljoy/pytorch-cqrn
Author: syljoy
Author-email: syljoy@163.com
License: MIT License
Platform: UNKNOWN
Requires-Python: >=3
License-File: LICENSE
